game_prediction/__init__.py
game_prediction/__init__.pyi
game_prediction/_beam_search.py
game_prediction/decoding.py
game_prediction/realtime.py
game_prediction/scores.py
game_prediction-0.1.1.dist-info/METADATA
game_prediction-0.1.1.dist-info/WHEEL
game_prediction-0.1.1.dist-info/top_level.txt
game_prediction-0.1.1.dist-info/RECORD
